[
  {
    "headline": "Etsy sells second-hand fashion app Depop to eBay for $1.2bn",
    "link": "https://www.bbc.com/news/articles/cx240kme2k8o?at_medium=RSS&at_campaign=rss",
    "source": "bbc",
    "pubdate": "2026-02-19-11-07-24 +0000"
  },
  {
    "headline": "Etsy sells second-hand fashion app Depop to eBay for $1.2bn",
    "link": "https://www.bbc.com/news/articles/cx240kme2k8o?at_medium=RSS&at_campaign=rss",
    "source": "bbc",
    "pubdate": "2026-02-19-11-07-24 +0000"
  },
  {
    "headline": "Live Updates: U.K. Police Arrest Former Prince Andrew Over Epstein Ties, BBC Reports",
    "link": "https://www.nytimes.com/live/2026/02/19/world/uk-prince-andrew-arrest-epstein",
    "source": "nyt",
    "pubdate": "2026-02-19-11-06-44 +0000"
  },
  {
    "headline": "Live Updates: South Korean Ex-Leader Is Sentenced to Life in Prison",
    "link": "https://www.nytimes.com/live/2026/02/19/world/yoon-korea-martial-law-president",
    "source": "nyt",
    "pubdate": "2026-02-19-11-03-38 +0000"
  },
  {
    "headline": "Besides Yoon, 5 other former officials get long prison terms.",
    "link": "https://www.nytimes.com/live/2026/02/19/world/yoon-korea-martial-law-president/besides-yoon-5-other-former-officials-get-long-prison-terms",
    "source": "nyt",
    "pubdate": "2026-02-19-11-03-36 +0000"
  },
  {
    "headline": "Besides Yoon, 5 other former officials get long prison terms.",
    "link": "https://www.nytimes.com/live/2026/02/19/world/yoon-korea-martial-law-president/besides-yoon-5-other-former-officials-get-long-prison-terms",
    "source": "nyt",
    "pubdate": "2026-02-19-11-03-36 +0000"
  },
  {
    "headline": "Here’s the latest.",
    "link": "https://www.nytimes.com/live/2026/02/19/world/uk-prince-andrew-arrest-epstein/uk-police-arrest-prince-andrew-epstein",
    "source": "nyt",
    "pubdate": "2026-02-19-11-03-33 +0000"
  },
  {
    "headline": "Here’s the latest.",
    "link": "https://www.nytimes.com/live/2026/02/19/world/uk-prince-andrew-arrest-epstein/uk-police-arrest-prince-andrew-epstein",
    "source": "nyt",
    "pubdate": "2026-02-19-11-03-33 +0000"
  },
  {
    "headline": "Billionaire Les Wexner tells US lawmakers he was 'naive' and 'conned' by Epstein",
    "link": "https://www.bbc.com/news/articles/cy57rrrpvg7o?at_medium=RSS&at_campaign=rss",
    "source": "bbc",
    "pubdate": "2026-02-19-11-01-07 +0000"
  },
  {
    "headline": "Billionaire Les Wexner tells US lawmakers he was 'naive' and 'conned' by Epstein",
    "link": "https://www.bbc.com/news/articles/cy57rrrpvg7o?at_medium=RSS&at_campaign=rss",
    "source": "bbc",
    "pubdate": "2026-02-19-11-01-07 +0000"
  },
  {
    "headline": "Former Prince Andrew Arrested Over Epstein Probe, BBC Reports",
    "link": "https://www.wsj.com/world/uk/former-prince-andrew-arrested-over-epstein-probe-bbc-reports-7779cc1e",
    "source": "wsj",
    "pubdate": "2026-02-19-11-01-00 +0000"
  },
  {
    "headline": "NYC’s most poop-filled areas revealed — as dog waste complaints hit record highs",
    "link": "https://nypost.com/2026/02/19/us-news/nycs-most-poop-filled-areas-revealed-as-dog-waste-complaints-hit-record-highs/",
    "source": "nypost",
    "pubdate": "2026-02-19-11-00-00 +0000"
  },
  {
    "headline": "PM says 'nobody is above the law' over Andrew allegations",
    "link": "https://www.bbc.com/news/articles/crm83kkrn9xo?at_medium=RSS&at_campaign=rss",
    "source": "bbc",
    "pubdate": "2026-02-19-10-56-46 +0000"
  },
  {
    "headline": "Warmer weather hits profits at British Gas owner",
    "link": "https://www.bbc.com/news/articles/cz7g9ge2lr2o?at_medium=RSS&at_campaign=rss",
    "source": "bbc",
    "pubdate": "2026-02-19-10-52-16 +0000"
  },
  {
    "headline": "Warmer weather hits profits at British Gas owner",
    "link": "https://www.bbc.com/news/articles/cz7g9ge2lr2o?at_medium=RSS&at_campaign=rss",
    "source": "bbc",
    "pubdate": "2026-02-19-10-52-16 +0000"
  },
  {
    "headline": "Starmer says Reform UK plans to repeal Equality Act 'shocking'",
    "link": "https://www.bbc.com/news/articles/c9dnjg896zno?at_medium=RSS&at_campaign=rss",
    "source": "bbc",
    "pubdate": "2026-02-19-10-50-53 +0000"
  },
  {
    "headline": "U.S. Treasury Yields Rise as Fed Minutes Reduce Rate-Cut Prospects",
    "link": "https://www.wsj.com/opinion/jgb-futures-fall-tracking-declines-in-u-s-treasury-market-a31a880b?mod=rss_markets_main",
    "source": "wsj",
    "pubdate": "2026-02-19-10-50-00 +0000"
  },
  {
    "headline": "U.S. Treasury Yields Rise as Fed Minutes Reduce Rate-Cut Prospects",
    "link": "https://www.wsj.com/opinion/jgb-futures-fall-tracking-declines-in-u-s-treasury-market-a31a880b",
    "source": "wsj",
    "pubdate": "2026-02-19-10-50-00 +0000"
  },
  {
    "headline": "Detained Briton describes life in Iran jail to BBC hours before sentencing",
    "link": "https://www.bbc.com/news/articles/c747nqply93o?at_medium=RSS&at_campaign=rss",
    "source": "bbc",
    "pubdate": "2026-02-19-10-49-47 +0000"
  },
  {
    "headline": "Samba school that praised Brazil's Lula  at Rio Carnival relegated",
    "link": "https://www.bbc.com/news/articles/c3ewvz0j87zo?at_medium=RSS&at_campaign=rss",
    "source": "bbc",
    "pubdate": "2026-02-19-10-47-09 +0000"
  },
  {
    "headline": "Samba school that praised Brazil's Lula  at Rio Carnival relegated",
    "link": "https://www.bbc.com/news/articles/c3ewvz0j87zo?at_medium=RSS&at_campaign=rss",
    "source": "bbc",
    "pubdate": "2026-02-19-10-47-09 +0000"
  },
  {
    "headline": "Europe Worries About Another Trump Blowup, This One on Tech",
    "link": "https://www.nytimes.com/2026/02/19/world/europe/europe-united-states-trump-digital-services-act.html",
    "source": "nyt",
    "pubdate": "2026-02-19-10-44-35 +0000"
  },
  {
    "headline": "Europe Worries About Another Trump Blowup, This One on Tech",
    "link": "https://www.nytimes.com/2026/02/19/world/europe/europe-united-states-trump-digital-services-act.html",
    "source": "nyt",
    "pubdate": "2026-02-19-10-44-35 +0000"
  },
  {
    "headline": "Over 1,000 Kenyans enlisted to fight in Russia-Ukraine war, report says",
    "link": "https://www.bbc.com/news/articles/ce8w266769go?at_medium=RSS&at_campaign=rss",
    "source": "bbc",
    "pubdate": "2026-02-19-10-44-14 +0000"
  },
  {
    "headline": "Former prince Andrew arrested on suspicion of misconduct in office, news reports say",
    "link": "https://www.washingtonpost.com/world/2026/02/19/uk-police-arrest-ex-royal-prince-andrew/",
    "source": "wapo",
    "pubdate": "2026-02-19-10-40-56 +0000"
  },
  {
    "headline": "Democrats revive a once-taboo idea: Capping grocery prices",
    "link": "https://www.washingtonpost.com/business/2026/02/19/price-freeze-groceries-inflation/",
    "source": "wapo",
    "pubdate": "2026-02-19-10-30-52 +0000"
  },
  {
    "headline": "Uber, Latest Victim of Disruption Panic, Still Has Role in Robotaxis",
    "link": "https://www.wsj.com/tech/uber-latest-victim-of-disruption-panic-still-has-role-in-robotaxis-7cb07d60?mod=pls_whats_news_us_business_f",
    "source": "wsj",
    "pubdate": "2026-02-19-10-30-00 +0000"
  },
  {
    "headline": "What to Make of This Very Weird Market",
    "link": "https://www.wsj.com/finance/stocks/what-to-make-of-this-very-weird-market-3c42f4fb?mod=rss_markets_main",
    "source": "wsj",
    "pubdate": "2026-02-19-10-30-00 +0000"
  },
  {
    "headline": "Uber, Latest Victim of Disruption Panic, Still Has Role in Robotaxis",
    "link": "https://www.wsj.com/tech/uber-latest-victim-of-disruption-panic-still-has-role-in-robotaxis-7cb07d60?mod=rss_markets_main",
    "source": "wsj",
    "pubdate": "2026-02-19-10-30-00 +0000"
  },
  {
    "headline": "Utah ‘dance mom’ who killed daughter at cheer competition had visits cut, record of violence — but still had parental control",
    "link": "https://nypost.com/2026/02/19/us-news/tawnia-mcgeehan-had-visits-with-slain-daughter-cut-record-of-violence/",
    "source": "nypost",
    "pubdate": "2026-02-19-10-30-00 +0000"
  },
  {
    "headline": "Starmer appoints Romeo as head of UK civil service",
    "link": "https://www.bbc.com/news/articles/c3rz8z33rqxo?at_medium=RSS&at_campaign=rss",
    "source": "bbc",
    "pubdate": "2026-02-19-10-28-16 +0000"
  },
  {
    "headline": "Former prince Andrew Mountbatten-Windsor arrested by U.K. police",
    "link": "https://www.cbc.ca/news/livestory/andrew-mountbatten-windsor-arrest-uk-police-epstein-files-9.7096935?cmp=rss",
    "source": "cbc",
    "pubdate": "2026-02-19-10-22-20 +0000"
  },
  {
    "headline": "Basic Materials Roundup: Market Talk",
    "link": "https://www.wsj.com/business/basic-materials-roundup-market-talk-e9fae190?mod=rss_markets_main",
    "source": "wsj",
    "pubdate": "2026-02-19-10-15-00 +0000"
  },
  {
    "headline": "Ex-Prince Andrew arrested by UK police over Epstein-linked allegations: Report",
    "link": "https://nypost.com/2026/02/19/world-news/ex-prince-andrew-mountbatten-arrested-for-misconduct-in-public-office-over-his-links-to-jeffrey-epstein/",
    "source": "nypost",
    "pubdate": "2026-02-19-10-15-00 +0000"
  }
]