[
  {
    "headline": "Stocks Tumble as Inflation Risk Emerges in Wake of Iran War",
    "link": "https://www.nytimes.com/2026/03/03/world/middleeast/stock-markets-iran.html",
    "source": "nyt",
    "pubdate": "2026-03-03-15-06-48 +0000"
  },
  {
    "headline": "Live: Kristi Noem won’t retract ‘domestic terrorist’ label of of Minnesotans killed by federal agents",
    "link": "https://www.startribune.com/ice-raids-minnesota/601546426",
    "source": "startribune",
    "pubdate": "2026-03-03-15-04-40 +0000"
  },
  {
    "headline": "Live Updates: U.S. Closes 2 Gulf Embassies; Israel Seizes Sites in Southern Lebanon",
    "link": "https://www.nytimes.com/live/2026/03/03/world/iran-war-israel-lebanon-trump",
    "source": "nyt",
    "pubdate": "2026-03-03-15-03-56 +0000"
  },
  {
    "headline": "Here’s the latest.",
    "link": "https://www.nytimes.com/live/2026/03/03/world/iran-war-israel-lebanon-trump/heres-the-latest",
    "source": "nyt",
    "pubdate": "2026-03-03-15-02-57 +0000"
  },
  {
    "headline": "Here’s the latest.",
    "link": "https://www.nytimes.com/live/2026/03/03/world/iran-war-israel-lebanon-trump/heres-the-latest",
    "source": "nyt",
    "pubdate": "2026-03-03-15-02-57 +0000"
  },
  {
    "headline": "Iran’s Strategy: Expand the War, Increase the Cost, Outlast Trump",
    "link": "https://www.nytimes.com/2026/03/03/world/europe/iran-war-strategy-trump-israel.html",
    "source": "nyt",
    "pubdate": "2026-03-03-14-59-12 +0000"
  },
  {
    "headline": "Iran’s Strategy: Expand the War, Increase the Cost, Outlast Trump",
    "link": "https://www.nytimes.com/2026/03/03/world/europe/iran-war-strategy-trump-israel.html",
    "source": "nyt",
    "pubdate": "2026-03-03-14-59-12 +0000"
  },
  {
    "headline": "U.S. and Israeli airstrikes targeted the office of the Assembly of Experts in Qom, south of...",
    "link": "https://www.washingtonpost.com",
    "source": "wapo",
    "pubdate": "2026-03-03-14-54-44 +0000"
  },
  {
    "headline": "Live updates: Iran strikes prompt closure of U.S. embassies in Saudi Arabia and Kuwait; Israel attacks Lebanon",
    "link": "https://www.washingtonpost.com/world/2026/03/03/us-iran-israel-military-strikes-trump-live-updates/",
    "source": "wapo",
    "pubdate": "2026-03-03-14-54-44 +0000"
  },
  {
    "headline": "Why did US and Israel attack Iran and how long could the war last?",
    "link": "https://www.bbc.com/news/articles/cx2dyz6p3weo?at_medium=RSS&at_campaign=rss",
    "source": "bbc",
    "pubdate": "2026-03-03-14-53-59 +0000"
  },
  {
    "headline": "Why did US and Israel attack Iran and how long could the war last?",
    "link": "https://www.bbc.com/news/articles/cx2dyz6p3weo?at_medium=RSS&at_campaign=rss",
    "source": "bbc",
    "pubdate": "2026-03-03-14-53-59 +0000"
  },
  {
    "headline": "Target Sales Just Fell Again. Now Its New CEO Plans for Turnaround.",
    "link": "https://www.wsj.com/business/retail/target-tgt-earnings-q4-2025-d800c864?mod=pls_whats_news_us_business_f",
    "source": "wsj",
    "pubdate": "2026-03-03-14-50-00 +0000"
  },
  {
    "headline": "Gas and oil prices soar and shares tumble on fears conflict could escalate",
    "link": "https://www.bbc.com/news/articles/cr5lz0vgy52o?at_medium=RSS&at_campaign=rss",
    "source": "bbc",
    "pubdate": "2026-03-03-14-49-05 +0000"
  },
  {
    "headline": "Gas and oil prices soar and shares tumble on fears conflict could escalate",
    "link": "https://www.bbc.com/news/articles/cr5lz0vgy52o?at_medium=RSS&at_campaign=rss",
    "source": "bbc",
    "pubdate": "2026-03-03-14-49-05 +0000"
  },
  {
    "headline": "Gas and oil prices soar and shares tumble on fears conflict could escalate",
    "link": "https://www.bbc.com/news/articles/cr5lz0vgy52o?at_medium=RSS&at_campaign=rss",
    "source": "bbc",
    "pubdate": "2026-03-03-14-49-05 +0000"
  },
  {
    "headline": "Reeves says her plan is working as growth forecast cut for this year",
    "link": "https://www.bbc.com/news/articles/ce8wew99ngpo?at_medium=RSS&at_campaign=rss",
    "source": "bbc",
    "pubdate": "2026-03-03-14-47-44 +0000"
  },
  {
    "headline": "Global Markets Tumble as Iran War Intensifies",
    "link": "https://www.nytimes.com/2026/03/03/world/middleeast/stock-markets-iran.html",
    "source": "nyt",
    "pubdate": "2026-03-03-14-45-23 +0000"
  },
  {
    "headline": "Stocks Slide as Oil Prices Jump",
    "link": "https://www.wsj.com/finance/inflation-fears-spark-selloff-as-middle-east-conflict-enters-fourth-day-3906026a?mod=pls_whats_news_us_business_f",
    "source": "wsj",
    "pubdate": "2026-03-03-14-44-00 +0000"
  },
  {
    "headline": "Stocks Slide as Oil Prices Jump",
    "link": "https://www.wsj.com/finance/inflation-fears-spark-selloff-as-middle-east-conflict-enters-fourth-day-3906026a?mod=rss_markets_main",
    "source": "wsj",
    "pubdate": "2026-03-03-14-44-00 +0000"
  },
  {
    "headline": "Iran strikes the US Embassy in Saudi Arabia as war expands yet again",
    "link": "https://www.startribune.com/us-embassy-in-saudi-arabia-hit-with-iranian-drones-as-american-and-israeli-attacks-on-iran-escalate/601591717",
    "source": "startribune",
    "pubdate": "2026-03-03-14-42-12 +0000"
  },
  {
    "headline": "Oil and Natural Gas Prices Extend Rally as Iran Attacks Escalates",
    "link": "https://www.nytimes.com/2026/03/03/business/energy-environment/oil-natural-gas-iran-israel-united-states.html",
    "source": "nyt",
    "pubdate": "2026-03-03-14-39-44 +0000"
  },
  {
    "headline": "Oil and Natural Gas Prices Extend Rally as Iran Attacks Escalates",
    "link": "https://www.nytimes.com/2026/03/03/business/energy-environment/oil-natural-gas-iran-israel-united-states.html",
    "source": "nyt",
    "pubdate": "2026-03-03-14-39-44 +0000"
  },
  {
    "headline": "Oil and Natural Gas Prices Extend Rally as Iran Attacks Escalates",
    "link": "https://www.nytimes.com/2026/03/03/business/energy-environment/oil-natural-gas-iran-israel-united-states.html",
    "source": "nyt",
    "pubdate": "2026-03-03-14-39-44 +0000"
  },
  {
    "headline": "Here’s the latest.",
    "link": "https://www.nytimes.com/live/2026/03/03/us/election-midterms-tx-nc-ar/heres-the-latest",
    "source": "nyt",
    "pubdate": "2026-03-03-14-38-00 +0000"
  },
  {
    "headline": "Higher Energy Prices Could Impact Sterling, Euro",
    "link": "https://www.wsj.com/finance/currencies/asian-currencies-mixed-might-be-weighed-by-continuing-geopolitical-risks-d4e8dbed?mod=rss_markets_main",
    "source": "wsj",
    "pubdate": "2026-03-03-14-34-00 +0000"
  },
  {
    "headline": "Risk to Middle East Oil Infrastructure Adds to Disruption Concerns",
    "link": "https://www.wsj.com/finance/commodities-futures/oil-rises-as-middle-east-conflict-keeps-supply-disruption-risks-elevated-b98faeaa?mod=rss_markets_main",
    "source": "wsj",
    "pubdate": "2026-03-03-14-33-00 +0000"
  },
  {
    "headline": "U.S. and Israel Striking Iran Security Agencies That Helped Crush Protests",
    "link": "https://www.nytimes.com/2026/03/03/world/middleeast/us-israel-strikes-iran-state-security-police.html",
    "source": "nyt",
    "pubdate": "2026-03-03-14-32-15 +0000"
  },
  {
    "headline": "U.S. and Israel Striking Iran Security Agencies That Helped Crush Protests",
    "link": "https://www.nytimes.com/2026/03/03/world/middleeast/us-israel-strikes-iran-state-security-police.html",
    "source": "nyt",
    "pubdate": "2026-03-03-14-32-15 +0000"
  },
  {
    "headline": "UK considers sending Royal Navy warship to Cyprus",
    "link": "https://www.bbc.com/news/articles/c4g40yp2p13o?at_medium=RSS&at_campaign=rss",
    "source": "bbc",
    "pubdate": "2026-03-03-14-28-47 +0000"
  },
  {
    "headline": "Spring Statement 2026: Key points at a glance",
    "link": "https://www.bbc.com/news/articles/c5yv255914xo?at_medium=RSS&at_campaign=rss",
    "source": "bbc",
    "pubdate": "2026-03-03-14-27-04 +0000"
  },
  {
    "headline": "Spring Statement 2026: Key points at a glance",
    "link": "https://www.bbc.com/news/articles/c5yv255914xo?at_medium=RSS&at_campaign=rss",
    "source": "bbc",
    "pubdate": "2026-03-03-14-27-04 +0000"
  },
  {
    "headline": "Supreme Court Sides With Religious Parents, Blocking California’s Trans Student Policy",
    "link": "https://www.nytimes.com/2026/03/02/us/politics/supreme-court-california-trans-students.html",
    "source": "nyt",
    "pubdate": "2026-03-03-14-21-20 +0000"
  },
  {
    "headline": "Supreme Court Sides With Religious Parents, Blocking California’s Trans Student Policy",
    "link": "https://www.nytimes.com/2026/03/02/us/politics/supreme-court-california-trans-students.html",
    "source": "nyt",
    "pubdate": "2026-03-03-14-21-20 +0000"
  },
  {
    "headline": "Ukrainian President Volodymyr Zelensky said he had discussed “how we can help in this situation” with...",
    "link": "https://www.washingtonpost.com",
    "source": "wapo",
    "pubdate": "2026-03-03-14-18-03 +0000"
  },
  {
    "headline": "South Texas Democratic Primary Tests Latino Vote",
    "link": "https://www.nytimes.com/2026/03/03/us/elections/texas-district-15-primary-election.html",
    "source": "nyt",
    "pubdate": "2026-03-03-14-17-55 +0000"
  },
  {
    "headline": "Has Your Business Been Affected by Immigration Policies? We Want to Hear From You.",
    "link": "https://www.nytimes.com/2026/03/03/us/politics/immigration-business-questions.html",
    "source": "nyt",
    "pubdate": "2026-03-03-14-17-26 +0000"
  },
  {
    "headline": "Has Your Business Been Affected by Immigration Policies? We Want to Hear From You.",
    "link": "https://www.nytimes.com/2026/03/03/us/politics/immigration-business-questions.html",
    "source": "nyt",
    "pubdate": "2026-03-03-14-17-26 +0000"
  },
  {
    "headline": "Has Your Business Been Affected by Immigration Policies? We Want to Hear From You.",
    "link": "https://www.nytimes.com/2026/03/03/us/politics/immigration-business-questions.html",
    "source": "nyt",
    "pubdate": "2026-03-03-14-17-26 +0000"
  },
  {
    "headline": "How the Bombing of Iran Is Affecting Lebanon, Kuwait and Other Countries",
    "link": "https://www.nytimes.com/2026/03/02/world/middleeast/iran-attacks-damage-what-to-know.html",
    "source": "nyt",
    "pubdate": "2026-03-03-14-15-50 +0000"
  },
  {
    "headline": "How the Bombing of Iran Is Affecting Lebanon, Kuwait and Other Countries",
    "link": "https://www.nytimes.com/2026/03/02/world/middleeast/iran-attacks-damage-what-to-know.html",
    "source": "nyt",
    "pubdate": "2026-03-03-14-15-50 +0000"
  },
  {
    "headline": "Ford and G.M. Face a Dilemma as China Excels in Electric Vehicles",
    "link": "https://www.nytimes.com/2026/03/03/business/ford-gm-ev-self-driving-cars-china.html",
    "source": "nyt",
    "pubdate": "2026-03-03-14-15-38 +0000"
  },
  {
    "headline": "Ford and G.M. Face a Dilemma as China Excels in Electric Vehicles",
    "link": "https://www.nytimes.com/2026/03/03/business/ford-gm-ev-self-driving-cars-china.html",
    "source": "nyt",
    "pubdate": "2026-03-03-14-15-38 +0000"
  },
  {
    "headline": "Ford and G.M. Face a Dilemma as China Excels in Electric Vehicles",
    "link": "https://www.nytimes.com/2026/03/03/business/ford-gm-ev-self-driving-cars-china.html",
    "source": "nyt",
    "pubdate": "2026-03-03-14-15-38 +0000"
  },
  {
    "headline": "Ford and G.M. Face a Dilemma as China Excels in Electric Vehicles",
    "link": "https://www.nytimes.com/2026/03/03/business/ford-gm-ev-self-driving-cars-china.html",
    "source": "nyt",
    "pubdate": "2026-03-03-14-15-38 +0000"
  },
  {
    "headline": "Texas and North Carolina Elections Will Test Older House Democrats’ Staying Power",
    "link": "https://www.nytimes.com/2026/03/03/us/politics/texas-north-carolina-older-democrats.html",
    "source": "nyt",
    "pubdate": "2026-03-03-14-12-24 +0000"
  },
  {
    "headline": "Texas and North Carolina Elections Will Test Older House Democrats’ Staying Power",
    "link": "https://www.nytimes.com/2026/03/03/us/politics/texas-north-carolina-older-democrats.html",
    "source": "nyt",
    "pubdate": "2026-03-03-14-12-24 +0000"
  },
  {
    "headline": "Crockett vs. Talarico. Progressive vs. Moderate. Right?",
    "link": "https://www.nytimes.com/2026/03/03/upshot/crockett-talarico-texas-senate-election.html",
    "source": "nyt",
    "pubdate": "2026-03-03-14-12-07 +0000"
  }
]