[
  {
    "headline": "Will your job be replaced by AI?  Here are the roles most affected",
    "link": "https://www.bbc.co.uk/news/articles/cn7nllr4vd6o?at_medium=RSS&at_campaign=rss",
    "source": "bbc",
    "pubdate": "2026-07-22-07-40-33 +0000"
  },
  {
    "headline": "Fifth person dies in Legionnaires’ disease outbreak in NYC",
    "link": "https://nypost.com/2026/07/22/us-news/nyc-legionnaires-disease-outbreak-claims-5th-death/",
    "source": "nypost",
    "pubdate": "2026-07-22-07-40-19 +0000"
  },
  {
    "headline": "More Russian online retailer Wildberries sites hit by Ukrainian drones",
    "link": "https://www.bbc.co.uk/news/articles/c36de9n4pxpo?at_medium=RSS&at_campaign=rss",
    "source": "bbc",
    "pubdate": "2026-07-22-07-38-20 +0000"
  },
  {
    "headline": "More warehouses of Russian online retailer Wildberries hit by Ukraine, officials say",
    "link": "https://www.bbc.co.uk/news/articles/c36de9n4pxpo?at_medium=RSS&at_campaign=rss",
    "source": "bbc",
    "pubdate": "2026-07-22-07-38-20 +0000"
  },
  {
    "headline": "Kloeckner Says Boards View Worthington’s Delisting Bid Favorably",
    "link": "https://www.wsj.com/business/deals/kloeckner-says-boards-view-worthingtons-delisting-bid-favorably-182766d6?mod=pls_whats_news_us_business_f",
    "source": "wsj",
    "pubdate": "2026-07-22-07-31-00 +0000"
  },
  {
    "headline": "Streeting apologises after early prisoner release comments heard on mic",
    "link": "https://www.bbc.co.uk/news/articles/cgk4x44mm50o?at_medium=RSS&at_campaign=rss",
    "source": "bbc",
    "pubdate": "2026-07-22-07-30-05 +0000"
  },
  {
    "headline": "Food prices rise at slowest rate in nearly two years",
    "link": "https://www.bbc.co.uk/news/articles/ckg4xj8j5vjo?at_medium=RSS&at_campaign=rss",
    "source": "bbc",
    "pubdate": "2026-07-22-07-27-04 +0000"
  },
  {
    "headline": "Food prices rise at slowest rate in nearly two years",
    "link": "https://www.bbc.co.uk/news/articles/ckg4xj8j5vjo?at_medium=RSS&at_campaign=rss",
    "source": "bbc",
    "pubdate": "2026-07-22-07-27-04 +0000"
  },
  {
    "headline": "European Indexes Fall as Tech Rally Falters",
    "link": "https://www.wsj.com/finance/stocks/nikkei-rises-1-3-led-by-chip-metals-stocks-d4df2523?mod=rss_markets_main",
    "source": "wsj",
    "pubdate": "2026-07-22-07-22-00 +0000"
  },
  {
    "headline": "U.K. Inflation Falls to 15-Month Low",
    "link": "https://www.wsj.com/world/uk/u-k-inflation-falls-to-15-month-low-f4c30cec",
    "source": "wsj",
    "pubdate": "2026-07-22-07-13-00 +0000"
  },
  {
    "headline": "U.K. Inflation Falls to 15-Month Low",
    "link": "https://www.wsj.com/world/uk/u-k-inflation-falls-to-15-month-low-f4c30cec",
    "source": "wsj",
    "pubdate": "2026-07-22-07-13-00 +0000"
  },
  {
    "headline": "Dollar Remains Elevated as U.S.-Iran Conflict Lifts Energy Prices",
    "link": "https://www.wsj.com/finance/currencies/asian-currencies-consolidate-rising-oil-prices-treasury-yields-may-weigh-on-risk-sentiment-1691d3d5?mod=rss_markets_main",
    "source": "wsj",
    "pubdate": "2026-07-22-07-07-00 +0000"
  },
  {
    "headline": "Japan temperatures soar over 40C, marking first 'cruelly hot day'",
    "link": "https://www.bbc.co.uk/news/articles/cp3rz07grngo?at_medium=RSS&at_campaign=rss",
    "source": "bbc",
    "pubdate": "2026-07-22-07-00-24 +0000"
  },
  {
    "headline": "Japan temperatures soar over 40C, marking first 'cruelly hot day'",
    "link": "https://www.bbc.co.uk/news/articles/cp3rz07grngo?at_medium=RSS&at_campaign=rss",
    "source": "bbc",
    "pubdate": "2026-07-22-07-00-24 +0000"
  },
  {
    "headline": "Steve Hilton makes provocative plea to anti-Trump Californians: ‘You have a choice’",
    "link": "https://nypost.com/2026/07/22/us-news/steve-hilton-courts-anti-trump-voters-with-new-political-ads/",
    "source": "nypost",
    "pubdate": "2026-07-22-07-00-00 +0000"
  },
  {
    "headline": "Steve Hilton makes provocative plea to anti-Trump Californians: ‘You have a choice’",
    "link": "https://nypost.com/2026/07/22/us-news/steve-hilton-courts-anti-trump-voters-with-new-political-ads/",
    "source": "nypost",
    "pubdate": "2026-07-22-07-00-00 +0000"
  },
  {
    "headline": "Eurozone Bond Yields Rise as Oil Prices Move Higher",
    "link": "https://www.wsj.com/finance/investing/jgb-futures-fall-tracking-declines-in-u-s-treasury-market-54cd45d8?mod=rss_markets_main",
    "source": "wsj",
    "pubdate": "2026-07-22-06-59-00 +0000"
  },
  {
    "headline": "Wildfire Threatening Pleasanton Prompts Evacuation Order for Thousands",
    "link": "https://www.nytimes.com/2026/07/21/us/little-fire-pleasanton-ca.html",
    "source": "nyt",
    "pubdate": "2026-07-22-06-48-55 +0000"
  },
  {
    "headline": "How will Burnham fund £2 bus fare cap?",
    "link": "https://www.bbc.co.uk/news/videos/cdewk0je71go?at_medium=RSS&at_campaign=rss",
    "source": "bbc",
    "pubdate": "2026-07-22-06-47-46 +0000"
  },
  {
    "headline": "Virginia woman’s remains ID’d by DNA as police link 4 suspects to second alleged murder",
    "link": "https://nypost.com/2026/07/22/us-news/virginia-woman-helen-marie-pullen-banks-remains-idd-by-dna-as-police-link-4-suspects-to-second-alleged-murder/",
    "source": "nypost",
    "pubdate": "2026-07-22-06-46-37 +0000"
  },
  {
    "headline": "Fresnillo’s Gold, Silver Production Falls on Lower Ore Grades",
    "link": "https://www.wsj.com/business/fresnillos-gold-silver-production-falls-on-lower-ore-grades-a35290a9?mod=rss_markets_main",
    "source": "wsj",
    "pubdate": "2026-07-22-06-46-00 +0000"
  }
]