[
  {
    "headline": "Keir Starmer Resigns as UK Prime Minister",
    "link": "https://www.nytimes.com/2026/06/22/world/europe/keir-starmer-andy-burnham-prime-minister-britain.html",
    "source": "nyt",
    "pubdate": "2026-06-22-19-59-15 +0000"
  },
  {
    "headline": "Lionel Messi breaks World Cup scoring record with his 17th and 18th goals in Argentina win",
    "link": "https://www.startribune.com/lionel-messi-misses-penalty-kick-with-a-chance-to-break-the-world-cup-scoring-record-with-argentina/601860175",
    "source": "startribune",
    "pubdate": "2026-06-22-19-50-01 +0000"
  },
  {
    "headline": "Treasury Yields Rise as Middle East Talks Continue",
    "link": "https://www.wsj.com/finance/investing/jgb-yields-higher-amid-middle-east-uncertainty-ca344a8a?mod=rss_markets_main",
    "source": "wsj",
    "pubdate": "2026-06-22-19-50-00 +0000"
  },
  {
    "headline": "Shootout Suspect Is Dead After Killing Montreal Police Officer, Authorities Say",
    "link": "https://www.nytimes.com/2026/06/22/world/canada/montreal-shooting-manhunt-police.html",
    "source": "nyt",
    "pubdate": "2026-06-22-19-46-27 +0000"
  },
  {
    "headline": "Shootout Suspect Is Dead After Killing Montreal Police Officer, Authorities Say",
    "link": "https://www.nytimes.com/2026/06/22/world/canada/montreal-shooting-manhunt-police.html",
    "source": "nyt",
    "pubdate": "2026-06-22-19-46-27 +0000"
  },
  {
    "headline": "Starmer quits as Labour leader and paves way for contest for new prime minister",
    "link": "https://www.bbc.com/news/articles/cdxd00lg599o?at_medium=RSS&at_campaign=rss",
    "source": "bbc",
    "pubdate": "2026-06-22-19-44-27 +0000"
  },
  {
    "headline": "Pakistan Plans to Cut Tax on Menstrual Pads, but Many Say It’s Not Enough",
    "link": "https://www.nytimes.com/2026/06/22/world/asia/pakistan-menstrual-period-tax.html",
    "source": "nyt",
    "pubdate": "2026-06-22-19-43-49 +0000"
  },
  {
    "headline": "Pakistan Plans to Cut Tax on Menstrual Pads, but Many Say It’s Not Enough",
    "link": "https://www.nytimes.com/2026/06/22/world/asia/pakistan-menstrual-period-tax.html",
    "source": "nyt",
    "pubdate": "2026-06-22-19-43-49 +0000"
  },
  {
    "headline": "5 muggers repeatedly stab man in botched NYC robbery: cops",
    "link": "https://nypost.com/2026/06/22/us-news/5-muggers-repeatedly-stab-man-in-botched-nyc-robbery-cops/",
    "source": "nypost",
    "pubdate": "2026-06-22-19-43-29 +0000"
  },
  {
    "headline": "Clive Davis, Music Industry Titan Who Signed Whitney Houston, Dies at 94",
    "link": "https://www.nytimes.com/2026/06/22/arts/music/clive-davis-dead.html",
    "source": "nyt",
    "pubdate": "2026-06-22-19-41-19 +0000"
  },
  {
    "headline": "Fatal Tesla Crash Into Texas Home Now Under Federal Safety Investigation",
    "link": "https://www.wsj.com/business/autos/fatal-tesla-crash-into-texas-home-now-under-federal-safety-investigation-48cfeebe?mod=pls_whats_news_us_business_f",
    "source": "wsj",
    "pubdate": "2026-06-22-19-41-00 +0000"
  },
  {
    "headline": "Mideast Live Updates: U.S. Eases Sanctions on Iranian Oil, but Progress on Nuclear Issues Is Muddy",
    "link": "https://www.nytimes.com/live/2026/06/22/world/iran-us-trump-lebanon",
    "source": "nyt",
    "pubdate": "2026-06-22-19-40-41 +0000"
  },
  {
    "headline": "Vance Claims Progress in First Day of Iran Talks",
    "link": "https://www.nytimes.com/2026/06/22/world/middleeast/vance-iran-talks-progress.html",
    "source": "nyt",
    "pubdate": "2026-06-22-19-39-15 +0000"
  },
  {
    "headline": "Vance Claims Progress in First Day of Iran Talks",
    "link": "https://www.nytimes.com/2026/06/22/world/middleeast/vance-iran-talks-progress.html",
    "source": "nyt",
    "pubdate": "2026-06-22-19-39-15 +0000"
  },
  {
    "headline": "Power couple goes nuclear at posh Malibu boutique after owner dropped suspicious video",
    "link": "https://nypost.com/2026/06/22/us-news/la-power-couple-claps-back-after-alleged-malibu-boutique-stealing-scandal/",
    "source": "nypost",
    "pubdate": "2026-06-22-19-32-49 +0000"
  },
  {
    "headline": "Google loses $270B in market cap over concerns its ‘falling behind’ rivals in race for AI talent",
    "link": "https://nypost.com/2026/06/22/business/google-stock-loses-270b-in-value-over-concerns-its-falling-behind-rivals-in-race-for-ai-talent/",
    "source": "nypost",
    "pubdate": "2026-06-22-19-32-25 +0000"
  },
  {
    "headline": "U.S. Natural Gas Futures Advance on Weather Outlook",
    "link": "https://www.wsj.com/finance/commodities-futures/u-s-natural-gas-futures-gain-on-july-weather-outlook-f1b1e3ec?mod=rss_markets_main",
    "source": "wsj",
    "pubdate": "2026-06-22-19-32-00 +0000"
  },
  {
    "headline": "Donaldson trial in 60 seconds",
    "link": "https://www.bbc.com/news/videos/c2dyj7w7y21o?at_medium=RSS&at_campaign=rss",
    "source": "bbc",
    "pubdate": "2026-06-22-19-26-17 +0000"
  },
  {
    "headline": "Grieving family of teen tourist killed by horse carriage demand NYC ban rides: ‘Profound insult’",
    "link": "https://nypost.com/2026/06/22/us-news/romanch-mahajans-family-demands-nyc-ban-horse-carriages/",
    "source": "nypost",
    "pubdate": "2026-06-22-19-25-06 +0000"
  },
  {
    "headline": "MAGA base fractures over how Trump ended the Iran war: poll",
    "link": "https://nypost.com/2026/06/22/us-news/maga-base-fractures-over-how-trump-ended-the-iran-war-poll/",
    "source": "nypost",
    "pubdate": "2026-06-22-19-24-12 +0000"
  },
  {
    "headline": "MAGA base fractures over how Trump ended the Iran war: poll",
    "link": "https://nypost.com/2026/06/22/us-news/maga-base-fractures-over-how-trump-ended-the-iran-war-poll/",
    "source": "nypost",
    "pubdate": "2026-06-22-19-24-12 +0000"
  },
  {
    "headline": "Disturbing video shows Tesla crash into Texas home, killing grandma, 76, in latest Autopilot controversy",
    "link": "https://nypost.com/2026/06/22/business/disturbing-video-shows-tesla-crash-into-texas-home-killing-grandma-76-in-latest-autopilot-controversy/",
    "source": "nypost",
    "pubdate": "2026-06-22-19-23-24 +0000"
  },
  {
    "headline": "Fiancée of accused serial Boston rapist Matthew Nilo still standing by him as he appears for key hearing 3 years after arrest",
    "link": "https://nypost.com/2026/06/22/us-news/fiancee-of-accused-serial-boston-rape-suspect-matthew-nilo-still-standing-by-him-at-key-hearing/",
    "source": "nypost",
    "pubdate": "2026-06-22-19-19-32 +0000"
  },
  {
    "headline": "Here’s the latest.",
    "link": "https://www.nytimes.com/live/2026/06/22/world/iran-us-trump-lebanon/heres-the-latest",
    "source": "nyt",
    "pubdate": "2026-06-22-19-19-20 +0000"
  },
  {
    "headline": "Here’s the latest.",
    "link": "https://www.nytimes.com/live/2026/06/22/world/iran-us-trump-lebanon/heres-the-latest",
    "source": "nyt",
    "pubdate": "2026-06-22-19-19-20 +0000"
  },
  {
    "headline": "Oil Futures Retreat As U.S.-Iran Talks Make Some Headway",
    "link": "https://www.wsj.com/finance/commodities-futures/oil-prices-rise-as-doubts-over-u-s-iran-peace-deal-grow-bb9cd432?mod=rss_markets_main",
    "source": "wsj",
    "pubdate": "2026-06-22-19-18-00 +0000"
  },
  {
    "headline": "Definium’s shares surge 55% after LSD-based depression pill delivers strong results",
    "link": "https://nypost.com/2026/06/22/business/definiums-shares-surge-55-after-lsd-based-depression-pill-delivers-strong-results/",
    "source": "nypost",
    "pubdate": "2026-06-22-19-15-51 +0000"
  },
  {
    "headline": "Lionel Messi becomes all-time World Cup leading goalscorer after Argentina's 2-0 win over Austria",
    "link": "https://www.cbc.ca/sports/soccer/worldcup/fifa-world-cup-argentina-austria-recap-june-22-9.7244449?cmp=rss",
    "source": "cbc",
    "pubdate": "2026-06-22-19-12-43 +0000"
  },
  {
    "headline": "SCOTUS rules ex-LAPD cop, Instagram model can be sued by daughter of man she shot dead",
    "link": "https://nypost.com/2026/06/22/us-news/scotus-rules-ex-lapd-cop-instagram-model-can-be-sued-by-daughter-of-man-she-shot-dead/",
    "source": "nypost",
    "pubdate": "2026-06-22-19-09-09 +0000"
  },
  {
    "headline": "Harvey Milk Club joins 48 Hills for FREE Pride kick-off party this Wednesday!",
    "link": "https://48hills.org/2026/06/harvey-milk-club-joins-48-hills-for-free-pride-kick-off-party-this-wednesday/",
    "source": "48hills",
    "pubdate": "2026-06-22-19-08-08 +0000"
  },
  {
    "headline": "Judge Finds Justice Dept. Overreach in Subpoenas to Minnesota Officials",
    "link": "https://www.nytimes.com/2026/06/22/us/minnesota-democrats-judge-ruling.html",
    "source": "nyt",
    "pubdate": "2026-06-22-19-03-51 +0000"
  },
  {
    "headline": "Cheap Chinese AI models are quickly gaining customers across the US market: ‘This changes things’",
    "link": "https://nypost.com/2026/06/22/business/cheap-chinese-ai-models-are-quickly-gaining-customers-across-the-us-market/",
    "source": "nypost",
    "pubdate": "2026-06-22-19-01-08 +0000"
  },
  {
    "headline": "Taliban and E.U. Officials to Discuss Afghan Deportees in Brussels",
    "link": "https://www.nytimes.com/2026/06/22/world/europe/afganistan-taliban-brussels-deportees.html",
    "source": "nyt",
    "pubdate": "2026-06-22-19-00-15 +0000"
  },
  {
    "headline": "Taliban and E.U. Officials to Discuss Afghan Deportees in Brussels",
    "link": "https://www.nytimes.com/2026/06/22/world/europe/afganistan-taliban-brussels-deportees.html",
    "source": "nyt",
    "pubdate": "2026-06-22-19-00-15 +0000"
  },
  {
    "headline": "Taliban and E.U. Officials to Discuss Afghan Deportees in Brussels",
    "link": "https://www.nytimes.com/2026/06/22/world/europe/afganistan-taliban-brussels-deportees.html",
    "source": "nyt",
    "pubdate": "2026-06-22-19-00-15 +0000"
  },
  {
    "headline": "Netflix Buys a ‘Hot Ones’ Spinoff",
    "link": "https://www.nytimes.com/2026/06/22/business/media/hot-ones-sean-evans-netflix.html",
    "source": "nyt",
    "pubdate": "2026-06-22-19-00-06 +0000"
  }
]