[
  {
    "score": 34,
    "pubdate": "2026-05-24-09-00-00 +0000",
    "source": "wsj",
    "headline": "Texas Sen. John Cornyn’s primary runoff against firebrand state Attorney General Ken Paxton this week is being closely watched as a barometer of the Republican Party’s future in Texas and the country",
    "link": "https://www.wsj.com/politics/elections/texas-senate-race-trump-d8a54348"
  },
  {
    "score": 24,
    "pubdate": "2026-05-24-09-00-36 +0000",
    "source": "nyt",
    "headline": "How a Curious FIFA Deal Gave Fox a Huge Bargain for World Cup Broadcast Rights",
    "link": "https://www.nytimes.com/2026/05/24/world/europe/fifa-world-cup-fox-broadcast-rights.html"
  },
  {
    "score": 18,
    "pubdate": "2026-05-24-09-01-42 +0000",
    "source": "nyt",
    "headline": "UK Institute Is Hunting for Dangers Lurking in AI",
    "link": "https://www.nytimes.com/2026/05/24/technology/uk-ai-safety-institute.html"
  },
  {
    "score": 18,
    "pubdate": "2026-05-24-09-00-16 +0000",
    "source": "nyt",
    "headline": "As Rents Soar, Londoners Turn to Vacant Pubs, Offices and Police Stations",
    "link": "https://www.nytimes.com/2026/05/24/world/europe/london-guardianships-rent-cost-of-living.html"
  },
  {
    "score": 16,
    "pubdate": "2026-05-24-09-01-58 +0000",
    "source": "nyt",
    "headline": "Sanders and Ocasio-Cortez Try Boosting Progressives in Red Districts",
    "link": "https://www.nytimes.com/2026/05/24/us/politics/bernie-sanders-swing-district-liberals.html"
  },
  {
    "score": 16,
    "pubdate": "2026-05-24-09-02-05 +0000",
    "source": "nyt",
    "headline": "With Big Decisions Ahead, the Supreme Court Collides With a Testy Trump",
    "link": "https://www.nytimes.com/2026/05/24/us/politics/supreme-court-trump-vance.html"
  },
  {
    "score": 15,
    "pubdate": "2026-05-24-09-08-31 +0000",
    "source": "bbc",
    "headline": "Blast targeting train kills at least 20 in Pakistan",
    "link": "https://www.bbc.com/news/articles/cm2pkd58xldo?at_medium=RSS&at_campaign=rss"
  },
  {
    "score": 11,
    "pubdate": "2026-05-24-09-00-00 +0000",
    "source": "wapo",
    "headline": "Hims & Hers CEO is plotting new ways to upend traditional health care",
    "link": "https://www.washingtonpost.com/health/2026/05/24/weight-loss-compounder-hims-hers-is-shifting-wellness-longevity/"
  },
  {
    "score": 10,
    "pubdate": "2026-05-24-09-00-14 +0000",
    "source": "nyt",
    "headline": "At an LA Costco, Skateboarding and Learning About Loss",
    "link": "https://www.nytimes.com/2026/05/24/business/economy/costco-curbs-skateboarding-genx.html"
  },
  {
    "score": 9,
    "pubdate": "2026-05-24-09-31-31 +0000",
    "source": "nyt",
    "headline": "Iran War Live Updates: Trump Says Peace Deal Is Near",
    "link": "https://www.nytimes.com/live/2026/05/23/world/us-iran-war-trump"
  }
]