[
  {
    "score": 28,
    "pubdate": "2025-10-02-19-41-57 +0000",
    "source": "nyt",
    "headline": "Deadly Car Ramming and Stabbing at U.K. Synagogue Is Declared Terrorist Attack",
    "link": "https://www.nytimes.com/2025/10/02/world/europe/terrorist-attack-uk-synagogue-manchester.html"
  },
  {
    "score": 26,
    "pubdate": "2025-10-02-18-55-34 +0000",
    "source": "nyt",
    "headline": "Trump ‘Determined’ the U.S. Is Now in a War With Drug Cartels, Congress Is Told",
    "link": "https://www.nytimes.com/2025/10/02/us/politics/trump-drug-cartels-war.html"
  },
  {
    "score": 23,
    "pubdate": "2025-10-02-19-41-16 +0000",
    "source": "nypost",
    "headline": "Palestinian diplomat lives in luxury $11K-per-month NYC apartment, alarming Jewish neighbors",
    "link": "https://nypost.com/2025/10/02/us-news/palestinian-diplomat-lives-in-luxury-11k-per-month-nyc-apartment-alarming-jewish-neighbors/"
  },
  {
    "score": 21,
    "pubdate": "2025-10-02-19-05-24 +0000",
    "source": "nyt",
    "headline": "Democrats Pull Away From AIPAC, Reflecting a Broader Shift",
    "link": "https://www.nytimes.com/2025/10/02/us/politics/democrats-aipac.html"
  },
  {
    "score": 16,
    "pubdate": "2025-10-02-19-45-41 +0000",
    "source": "nypost",
    "headline": "Eric Adams’ ex-girlfriend spills intimate details about secret romance — including what she rubbed ‘for hours’ to calm him down",
    "link": "https://nypost.com/2025/10/02/us-news/eric-adams-ex-girlfriend-reveals-what-she-rubbed-for-hours-to-calm-him-down/"
  },
  {
    "score": 16,
    "pubdate": "2025-10-02-19-01-41 +0000",
    "source": "nyt",
    "headline": "‘Appalled,’ ‘horrified,’ ‘sickening’: Leaders and residents condemn the Manchester attack.",
    "link": "https://www.nytimes.com/live/2025/10/02/world/manchester-synagogue-stabbing-uk/appalled-horrified-sickening-leaders-and-residents-condemn-the-manchester-attack"
  },
  {
    "score": 16,
    "pubdate": "2025-10-02-19-39-22 +0000",
    "source": "nyt",
    "headline": "After Declining to Give Trump a Sword for King Charles, a Museum Leader Is Out",
    "link": "https://www.nytimes.com/2025/10/02/arts/design/trump-eisenhower-king-charles-sword.html"
  },
  {
    "score": 16,
    "pubdate": "2025-10-02-19-22-00 +0000",
    "source": "wsj",
    "headline": "President Trump is considering providing $10 billion or more in aid to U.S. farmers as the agriculture sector warns of economic fallout from his far-reaching tariffs, according to people familiar with the discussions",
    "link": "https://www.wsj.com/politics/policy/trump-explores-bailout-of-at-least-10-billion-for-u-s-farmers-258d2975"
  },
  {
    "score": 15,
    "pubdate": "2025-10-02-19-50-31 +0000",
    "source": "nyt",
    "headline": "No More Signs of Life From Rubble of Collapsed School in Indonesia",
    "link": "https://www.nytimes.com/2025/10/02/world/asia/indonesia-school-collapse.html"
  },
  {
    "score": 14,
    "pubdate": "2025-10-02-19-36-48 +0000",
    "source": "nyt",
    "headline": "I.C.E. Transfers 18 Migrants From Guantánamo, Emptying Detention Site",
    "link": "https://www.nytimes.com/2025/10/02/us/politics/migrants-guantanamo-detention-removal.html"
  }
]