[
  {
    "score": 45,
    "pubdate": "2026-02-17-09-48-00 +0000",
    "source": "wsj",
    "headline": "Jesse Jackson, the civil-rights activist and political leader, has died at 84. He was the first Black man to wage a nationwide presidential campaign.",
    "link": "https://www.wsj.com/politics/jesse-jackson-civil-rights-leader-and-democratic-presidential-candidate-dies-59eb285b"
  },
  {
    "score": 29,
    "pubdate": "2026-02-17-10-03-00 +0000",
    "source": "nyt",
    "headline": "Trump Sought Vast Budget Cuts. Congress Granted Few.",
    "link": "https://www.nytimes.com/2026/02/17/us/politics/trump-congress-budget-cuts.html"
  },
  {
    "score": 26,
    "pubdate": "2026-02-17-09-12-39 +0000",
    "source": "nyt",
    "headline": "Ukraine and Russia Hold New Round of Peace Talks, but Expectations Are Low",
    "link": "https://www.nytimes.com/2026/02/17/world/europe/ukraine-russia-peace-talks-switzerland.html"
  },
  {
    "score": 18,
    "pubdate": "2026-02-17-09-37-00 +0000",
    "source": "wsj",
    "headline": "European Gas Price Falls Despite Depleted Inventories",
    "link": "https://www.wsj.com/articles/european-gas-price-falls-despite-depleted-inventories-c92e9d18?mod=pls_whats_news_us_business_f"
  },
  {
    "score": 16,
    "pubdate": "2026-02-17-09-25-31 +0000",
    "source": "nyt",
    "headline": "Trump Said He’d End the War in Ukraine in a Day. It’s Harder Than He Thought.",
    "link": "https://www.nytimes.com/2026/02/17/world/europe/trump-ukraine-war-putin.html"
  },
  {
    "score": 15,
    "pubdate": "2026-02-17-10-06-36 +0000",
    "source": "bbc",
    "headline": "Five young people die in Spain apartment block fire",
    "link": "https://www.bbc.com/news/articles/c99jngpymyjo?at_medium=RSS&at_campaign=rss"
  },
  {
    "score": 15,
    "pubdate": "2026-02-17-09-13-51 +0000",
    "source": "nypost",
    "headline": "Woke Portland pizza restaurant hits diners with anti-ICE propaganda and bizarrely declares ‘food is political’",
    "link": "https://nypost.com/2026/02/17/us-news/woke-pizza-restaurant-hits-diners-with-anti-ice-propaganda-and-bizarrely-declares-food-is-political/"
  },
  {
    "score": 14,
    "pubdate": "2026-02-17-10-03-10 +0000",
    "source": "nyt",
    "headline": "The Drone Games: Flying Cameras Are Everywhere at the Winter Olympics",
    "link": "https://www.nytimes.com/2026/02/17/world/europe/drones-winter-olympics-milan-cortina.html"
  },
  {
    "score": 11,
    "pubdate": "2026-02-17-10-01-00 +0000",
    "source": "nyt",
    "headline": "Did That Bald Head Get Your Attention? One Start-Up Hopes So.",
    "link": "https://www.nytimes.com/2026/02/17/technology/did-that-bald-head-get-your-attention-one-start-up-hopes-so.html"
  },
  {
    "score": 10,
    "pubdate": "2026-02-17-09-57-09 +0000",
    "source": "bbc",
    "headline": "New nuclear talks between US and Iran begin in Geneva",
    "link": "https://www.bbc.com/news/articles/cwyknjnd706o?at_medium=RSS&at_campaign=rss"
  }
]