[
  {
    "score": 19,
    "pubdate": "2025-10-05-11-29-30 +0000",
    "source": "nyt",
    "headline": "Fire at Peacehaven Mosque Is Being Treated as Hate Crime, UK Police Say",
    "link": "https://www.nytimes.com/2025/10/05/world/europe/peacehaven-arson-mosque-england.html"
  },
  {
    "score": 17,
    "pubdate": "2025-10-05-11-32-25 +0000",
    "source": "bbc",
    "headline": "Trump authorises deployment of 300 National Guard troops to Chicago",
    "link": "https://www.bbc.com/news/articles/c2dnk0ee6pyo?at_medium=RSS&at_campaign=rss"
  },
  {
    "score": 14,
    "pubdate": "2025-10-05-11-28-32 +0000",
    "source": "nyt",
    "headline": "Russia Targets Ukraine’s Energy Infrastructure With Deadly Bombardment",
    "link": "https://www.nytimes.com/2025/10/05/world/europe/russia-ukraine-strikes-energy-lviv.html"
  },
  {
    "score": 11,
    "pubdate": "2025-10-05-11-00-00 +0000",
    "source": "startribune",
    "headline": "‘Dangerous and un-American’: Politicians deride Trump administration over leaked messages on deploying Army to Portland",
    "link": "https://www.startribune.com/dangerous-and-un-american-politicians-deride-trump-administration-over-leaked-messages-on-deploying-army-t-portland/601486185"
  },
  {
    "score": 6,
    "pubdate": "2025-10-05-11-00-00 +0000",
    "source": "wsj",
    "headline": "Do Cash Payments Help Poor Families?",
    "link": "https://www.wsj.com/personal-finance/cash-payments-experiments-low-income-54501ee2"
  },
  {
    "score": 6,
    "pubdate": "2025-10-05-11-00-00 +0000",
    "source": "missionlocal",
    "headline": "Here’s how to park on the new Valencia Street",
    "link": "https://missionlocal.org/2025/10/park-valencia-street/"
  },
  {
    "score": 5,
    "pubdate": "2025-10-05-11-00-00 +0000",
    "source": "wsj",
    "headline": "Lessons From Jackson, Mississippi, for Trump’s Crackdown on Urban Crime",
    "link": "https://www.wsj.com/us-news/trump-crime-jackson-mississippi-093eeafe"
  },
  {
    "score": 3,
    "pubdate": "2025-10-05-11-24-40 +0000",
    "source": "nyt",
    "headline": "Donald Trump, the Sports Fan",
    "link": "https://www.nytimes.com/2025/10/05/world/hostage-deal-israel-hamas-portland-syria.html"
  },
  {
    "score": 2,
    "pubdate": "2025-10-05-11-36-49 +0000",
    "source": "nyt",
    "headline": "Oktoberfest’s New Drip",
    "link": "https://www.nytimes.com/card/2025/10/03/world/europe/oktoberfests-new-drip"
  },
  {
    "score": 0,
    "pubdate": "2025-10-05-11-32-25 +0000",
    "source": "bbc",
    "headline": "Trump authorises deployment of 300 National Guard troops to Chicago",
    "link": "https://www.bbc.com/news/articles/c2dnk0ee6pyo?at_medium=RSS&at_campaign=rss"
  }
]