[
  {
    "score": 136,
    "pubdate": "2026-02-06-01-19-00 +0000",
    "source": "wsj",
    "headline": "President Trump announced that he wants the U.S. to negotiate a new strategic arms treaty following the lapse of the last major nuclear pact with Russia",
    "link": "https://www.wsj.com/politics/national-security/trump-calls-for-new-nuclear-pact-with-russia-as-previous-treaty-ends-eb3a4a9a"
  },
  {
    "score": 104,
    "pubdate": "2026-02-06-17-16-34 +0000",
    "source": "nyt",
    "headline": "Milan Winter Olympics Opening Ceremony: What Time to Watch, How to Watch, and More",
    "link": "https://www.nytimes.com/2026/02/06/world/europe/milan-winter-olympics-opening-ceremony-how-to-watch.html"
  },
  {
    "score": 78,
    "pubdate": "2026-02-06-16-54-39 +0000",
    "source": "nyt",
    "headline": "Russian General Is Shot in Latest Attack on a Top Military Leader in Moscow",
    "link": "https://www.nytimes.com/2026/02/06/world/europe/russian-general-shot-moscow-alekseyev.html"
  },
  {
    "score": 77,
    "pubdate": "2026-02-06-02-19-00 +0000",
    "source": "wsj",
    "headline": "The Justice Department released what it says is its final trove of files related to the late Jeffrey Epstein. Here are some takeaways on what we know so far.",
    "link": "https://www.wsj.com/us-news/law/what-we-know-so-far-about-the-latest-release-of-epstein-files-260dafba"
  },
  {
    "score": 61,
    "pubdate": "2026-02-06-17-59-08 +0000",
    "source": "bbc",
    "headline": "Talks with US set to continue after 'good beginning', Iran's foreign minister says",
    "link": "https://www.bbc.com/news/articles/cr57g1y8286o?at_medium=RSS&at_campaign=rss"
  },
  {
    "score": 57,
    "pubdate": "2026-02-06-14-42-50 +0000",
    "source": "nyt",
    "headline": "Savannah Guthrie’s Brother Renews Plea for Return of Their Missing Mother, Nancy",
    "link": "https://www.nytimes.com/2026/02/06/us/savannah-nancy-guthrie-missing-updates.html"
  },
  {
    "score": 54,
    "pubdate": "2026-02-06-19-00-05 +0000",
    "source": "latimes",
    "headline": "Chabria: Yes, Trump's video showing the Obamas as apes is racist. But it's also about the election",
    "link": "https://www.latimes.com/politics/story/2026-02-06/chabria-column-trump-racist-video-what-comes-next"
  },
  {
    "score": 53,
    "pubdate": "2026-02-06-01-00-00 +0000",
    "source": "wsj",
    "headline": "Current and former prosecutors say they can relate to the government lawyer who told a judge in open court that she was exhausted and “this job sucks”",
    "link": "https://www.wsj.com/politics/policy/justice-department-struggles-under-weight-of-immigration-crackdown-0ba2e6f0"
  },
  {
    "score": 52,
    "pubdate": "2026-02-06-00-15-16 +0000",
    "source": "nypost",
    "headline": "TrumpRx website launches as prez vows Americans will ‘save a fortune’ on everything from Ozempic to fertility treatments",
    "link": "https://nypost.com/2026/02/05/us-news/trumprx-website-launches-as-prez-vows-americans-will-pay-the-lowest-price-for-medication/"
  },
  {
    "score": 49,
    "pubdate": "2026-02-06-04-26-26 +0000",
    "source": "nypost",
    "headline": "AOC touts money for her NYC district in funding bill she voted against, announces plans to train ICE ‘legal observers’",
    "link": "https://nypost.com/2026/02/05/us-news/aoc-touts-money-for-her-new-york-district-included-in-government-funding-bill-she-voted-against-announces-plans-to-train-ice-legal-observers-at-queens-town-hall/"
  }
]