[
  {
    "score": 534,
    "pubdate": "2026-01-08-20-24-34 +0000",
    "source": "nyt",
    "headline": "Trump Addresses Venezuela, Greenland and Presidential Power in New York Times Interview",
    "link": "https://www.nytimes.com/2026/01/08/us/politics/trump-interview-power-morality.html"
  },
  {
    "score": 279,
    "pubdate": "2026-01-08-20-12-04 +0000",
    "source": "nypost",
    "headline": "Car attacks on ICE agents spiked by more than 3,200% in a year, DHS reveals after Minnesota ICE shooting",
    "link": "https://nypost.com/2026/01/08/us-news/car-attacks-on-ice-agents-spiked-by-more-than-3000-over-past-year/"
  },
  {
    "score": 208,
    "pubdate": "2026-01-07-10-00-00 +0000",
    "source": "wsj",
    "headline": "The welfare-fraud scandal that led Minnesota Gov. Tim Walz to abandon his 2026 re-election bid was already public when he was vetted for the 2024 Democratic presidential ticket",
    "link": "https://www.wsj.com/politics/elections/minnesota-tim-walz-scandal-harris-campaign-6bafc8cd"
  },
  {
    "score": 188,
    "pubdate": "2026-01-08-01-34-00 +0000",
    "source": "wsj",
    "headline": "The Trump administration told lawmakers that the Justice Department developed a new legal opinion to justify the operation to seize Venezuelan President Nicolás Maduro",
    "link": "https://www.wsj.com/politics/policy/trump-administration-draws-up-new-legal-justification-for-maduro-operation-295bc317"
  },
  {
    "score": 142,
    "pubdate": "2026-01-07-17-34-58 +0000",
    "source": "nypost",
    "headline": "US will control Venezuelan oil sales ‘indefinitely,’ energy secretary says",
    "link": "https://nypost.com/2026/01/07/business/us-will-control-venezuelan-oil-sales-indefinitely-energy-secretary-says/"
  },
  {
    "score": 111,
    "pubdate": "2026-01-04-11-00-00 +0000",
    "source": "latimes",
    "headline": "This California political leader wants federal immigration reform. First, she has to survive Trump",
    "link": "https://www.latimes.com/california/story/2026-01-04/this-california-political-leader-wants-federal-immigration-reform-first-she-has-to-survive-trump"
  },
  {
    "score": 109,
    "pubdate": "2026-01-08-20-10-00 +0000",
    "source": "wsj",
    "headline": "President Trump lashed out at five GOP senators after they sided with Democrats in advancing a motion designed to block him from taking further military action in Venezuela without explicit congressional approval",
    "link": "https://www.wsj.com/politics/policy/senate-votes-to-rein-in-trumps-war-powers-in-venezuela-f6138553"
  },
  {
    "score": 107,
    "pubdate": "2026-01-08-03-37-31 +0000",
    "source": "nyt",
    "headline": "China Touts Hainan, Its Duty-Free Island, Amid $1 Trillion Trade Surplus",
    "link": "https://www.nytimes.com/2026/01/07/business/china-hainan-island-duty-free.html"
  },
  {
    "score": 100,
    "pubdate": "2026-01-08-18-13-50 +0000",
    "source": "nypost",
    "headline": "Russia rejects Trump’s 20-point peace plan for Ukraine: ‘Forming a true axis of war’",
    "link": "https://nypost.com/2026/01/08/us-news/russia-rejects-trumps-20-point-peace-plan-for-ukraine-forming-a-true-axis-of-war/"
  },
  {
    "score": 100,
    "pubdate": "2026-01-07-19-57-13 +0000",
    "source": "cbc",
    "headline": "Protests escalate after ICE agent fatally shoots woman in Minneapolis",
    "link": "https://www.cbc.ca/news/world/livestory/ice-shooting-minneapolis-live-updates-9.7036845?cmp=rss"
  }
]